CS207/lab code/lab7/jkff.v
module jkff(Q, J, K, CLK);
input CLK;
input J;
input K;
output Q;
reg Q;

always@(posedge CLK) begin
    case ({J,K})
      0  : Q=Q;
      1  : Q=0;
      2  : Q=1;
      3  : Q=~Q;
        //default: 
    endcase
end
endmodule

CS207/lab code/lab7/jkff_tb.v
module jkff_tb;
reg CLK; 
reg J;
reg K; 
wire Q; 
initial CLK <= 1'b1;

always @(CLK) 
begin 
#1 CLK<=!CLK; 
end

jkff mysr(Q, J, K, CLK);
initial begin 
$dumpfile("jkff.vcd"); 
$dumpvars(0,jkff_tb); 
end

initial begin 
$monitor("%3t: J=%b, K=%b, Q = %b", $time,J,K, Q); 
#5 J <= 1'b0; K <= 1'b0;
#5 J <= 1'b1; K <= 1'b0; 
#5 J <= 1'b0; K <= 1'b0; 
#5 J <= 1'b0; K <= 1'b1; 
#5 J <= 1'b0; K <= 1'b0; 
#5 J <= 1'b1; K <= 1'b0; 
#5 J <= 1'b0; K <= 1'b0;
#5 J <= 1'b1; K <= 1'b1; 
#5 J <= 1'b1; K <= 1'b1; 
#5 $finish; 
end 
 endmodule

CS207/document.v/lab7/jkff.vcd
$date
	Wed Apr 08 12:45:33 2020
$end
$version
	Icarus Verilog
$end
$timescale
	1s
$end
$scope module jkff_tb $end
$var wire 1 ! Q $end
$var reg 1 " CLK $end
$var reg 1 # J $end
$var reg 1 $ K $end
$scope module mysr $end
$var wire 1 " CLK $end
$var wire 1 # J $end
$var wire 1 $ K $end
$var reg 1 ! Q $end
$upscope $end
$upscope $end
$enddefinitions $end
#0
$dumpvars
x$
x#
1"
x!
$end
#1
0"
#2
1"
#3
0"
#4
1"
#5
0"
0$
0#
#6
1"
#7
0"
#8
1"
#9
0"
#10
1!
1"
1#
#11
0"
#12
1"
#13
0"
#14
1"
#15
0"
0#
#16
1"
#17
0"
#18
1"
#19
0"
#20
0!
1"
1$
#21
0"
#22
1"
#23
0"
#24
1"
#25
0"
0$
#26
1"
#27
0"
#28
1"
#29
0"
#30
1!
1"
1#
#31
0"
#32
1"
#33
0"
#34
1"
#35
0"
0#
#36
1"
#37
0"
#38
1"
#39
0"
#40
0!
1"
1$
1#
#41
0"
#42
1!
1"
#43
0"
#44
0!
1"
#45
0"
#46
1!
1"
#47
0"
#48
0!
1"
#49
0"
#50
1!
1"
