CS207/lab code/lab9/learn/mealy.v
 module mealy(Y, A, B, X, clk); 
 output reg Y;
 output reg A, B; 
 input X; 
 input clk;

always @(X or A or B)
case({A, B, X}) 
 2, 4, 6: Y <= 1'd1;
 default: Y <= 1'd0; 
 endcase


always @(posedge clk) 
case({A, B, X}) 
 0, 2, 4, 6: {A, B} <= 2'b00;
 1: {A, B} <= 2'b01; 
 5, 7: {A, B} <= 2'b10; 
 3: {A, B} <= 2'b11; 
 default: {A, B} <= 2'b00; 
 endcase 
 endmodule



  module mealy_tb; 
  reg CLK; 
  reg X;
  wire y;
  wire [1:0] Q;
  initial begin 
  CLK <= 1'b0; 
  X <= 1'b0; 
  end
  always @(CLK) 
  begin 
  #1 CLK<=!CLK;
   end
 mealy mealy1(y, Q[1], Q[0], X, CLK);
initial begin 
$dumpfile("mealy.vcd"); 
$dumpvars(0, mealy_tb);
 end
initial begin
$monitor("%3t: X = %b, y = %b, Q[1] = %b, Q[0] = %b", $time, X, y, Q[0], Q[1]);
#2 X <= 1'b0; //00 48 
#2 X <= 1'b1; //01 49 
#2 X <= 1'b1; //11 50 
#2 X <= 1'b1; //10 51 
#2 X <= 1'b0; //10 52 
#2 X <= 1'b0; //00 53 
#2 X <= 1'b1; //01 54 
#2 X <= 1'b0; //00 55 
#2 X <= 1'b1; //01 56 
#2 X <= 1'b1; //11 57 
#2 X <= 1'b0; //00 58 
#2 $finish;
 end
  endmodule

CS207/lab code/lab9/learn/mealy.vcd
$date
	Tue Apr 21 20:12:14 2020
$end
$version
	Icarus Verilog
$end
$timescale
	1s
$end
$scope module mealy_tb $end
$var wire 1 ! y $end
$var wire 2 " Q [1:0] $end
$var reg 1 # CLK $end
$var reg 1 $ X $end
$scope module mealy1 $end
$var wire 1 $ X $end
$var wire 1 # clk $end
$var reg 1 % A $end
$var reg 1 & B $end
$var reg 1 ! Y $end
$upscope $end
$upscope $end
$enddefinitions $end
#0
$dumpvars
x&
x%
0$
0#
bx "
0!
$end
#1
0%
b0 "
0&
1#
#2
0#
#3
1#
#4
0#
1$
#5
b1 "
1&
1#
#6
0#
#7
b11 "
1%
1#
#8
0#
#9
b10 "
0&
1#
#10
1!
0#
0$
#11
0!
b0 "
0%
1#
#12
0#
#13
1#
#14
0#
1$
#15
b1 "
1&
1#
#16
1!
0#
0$
#17
0!
b0 "
0&
1#
#18
0#
1$
#19
b1 "
1&
1#
#20
0#
#21
b11 "
1%
1#
#22
1!
0#
0$
#23
0!
0%
b0 "
0&
1#
