CS207/lab code/lab4/waveform/waveform.v
module waveform(a,b,c);
output a,b,c;
reg a,b,c;

initial begin
$dumpfile("waveform.vcd");
$dumpvars(0, waveform);
end

initial begin
    #0  a=0;
    #5  a=1;
    #5 a=0;
    #5 a=1;
    #5 a=0;
    #30 $finish;
    end
    
initial begin
    #0  b=0;
    #20 b=1;
    #5  b=0;
    #15 b=1;
    #10 $finish;
    end

initial begin
    #0  c=0;
    #20 c=1;
    #10 c=0;
    #10 c=1;
    #20 $finish;
    end

//initial begin
//$monitor("TIME= %2t A = %b ",$time, a); 
//#50 $finish;
//end
endmodule

CS207/lab code/lab4/waveform/waveform.vcd
$date
	Tue Mar 17 20:01:54 2020
$end
$version
	Icarus Verilog
$end
$timescale
	1s
$end
$scope module waveform $end
$var reg 1 ! a $end
$var reg 1 " b $end
$var reg 1 # c $end
$upscope $end
$enddefinitions $end
#0
$dumpvars
0#
0"
0!
$end
#5
1!
#10
0!
#15
1!
#20
0!
1#
1"
#25
0"
#30
0#
#40
1#
1"
