CS207/document.v/lab10/countm.v
module countm(Q, M, clk);
input [7:0]M;
input clk;
output [7:0]Q;
reg [7:0]Q;



always @(posedge clk ) begin

if (Q==M-1) begin
    Q<=8'b00000000;
end
else begin
    case (Q) 
        0,1,2,3,4,5,6,7,8,9,10,11,12,13,14,15,16,17,18,19,20,21,22,23,24,25,26,27,28,29,30,31,32,33,
        34,35,36,37,38,39,40,41,42,43,44,45,46,47,48,49,50,51,52,53,54,55,56,57,58,59,60,61,62,63,64,
        65,66,67,68,69,70,71,72,73,74,75,76,77,78,79,80,81,82,83,84,85,86,87,88,89,90,91,92,93,94,95,96,
        97,98,99,100,101,102,103,104,105,106,107,108,109,110,111,112,113,114,115,116,117,118,119,120,121,122,
        123,124,125,126,127,128,129,130,131,132,133,134,135,136,137,138,139,140,141,142,143,144,145,146,
        147,148,149,150,151,152,153,154,155,156,157,158,159,160,161,162,163,164,165,166,167,168,169,170,
        171,172,173,174,175,176,177,178,179,180,181,182,183,184,185,186,187,188,189,190,191,192,193,194,
        195,196,197,198,199,200,201,202,203,204,205,206,207,208,209,210,211,212,213,214,215,216,217,218,
        219,220,221,222,223,224,225,226,227,228,229,230,231,232,233,234,235,236,237,238,239,240,241,242,
        243,244,245,246,247,248,249,250,251,252,253,254:Q=Q+1 ;
        default: Q<=8'b00000000;
    endcase
end
end
endmodule

CS207/document.v/lab10/countm_tb_2.v
module countm_tb; 
  reg CLK; 
  reg [7:0]M;
  wire [7:0]Q;

initial begin 
CLK<=1'b0; 
 end
initial begin
M<=8'b00010000;
end
 always @(CLK)
  begin 
  #1 CLK<=!CLK;
   end

 countm countm_1(Q, M,CLK);

 initial begin 
 $dumpfile("countm.vcd"); 
  $dumpvars(0, countm_tb); 
   end

 initial begin 
 #550 $finish; 
  end 
   endmodule

CS207/document.v/lab10/countm.vcd
$date
	Wed Apr 29 10:00:20 2020
$end
$version
	Icarus Verilog
$end
$timescale
	1s
$end
$scope module countm_tb $end
$var wire 8 ! Q [7:0] $end
$var reg 1 " CLK $end
$var reg 8 # M [7:0] $end
$scope module countm_1 $end
$var wire 8 $ M [7:0] $end
$var wire 1 " clk $end
$var reg 8 % Q [7:0] $end
$upscope $end
$upscope $end
$enddefinitions $end
#0
$dumpvars
bx %
b10000 $
b10000 #
0"
bx !
$end
#1
b0 !
b0 %
1"
#2
0"
#3
b1 !
b1 %
1"
#4
0"
#5
b10 !
b10 %
1"
#6
0"
#7
b11 !
b11 %
1"
#8
0"
#9
b100 !
b100 %
1"
#10
0"
#11
b101 !
b101 %
1"
#12
0"
#13
b110 !
b110 %
1"
#14
0"
#15
b111 !
b111 %
1"
#16
0"
#17
b1000 !
b1000 %
1"
#18
0"
#19
b1001 !
b1001 %
1"
#20
0"
#21
b1010 !
b1010 %
1"
#22
0"
#23
b1011 !
b1011 %
1"
#24
0"
#25
b1100 !
b1100 %
1"
#26
0"
#27
b1101 !
b1101 %
1"
#28
0"
#29
b1110 !
b1110 %
1"
#30
0"
#31
b1111 !
b1111 %
1"
#32
0"
#33
b0 !
b0 %
1"
#34
0"
#35
b1 !
b1 %
1"
#36
0"
#37
b10 !
b10 %
1"
#38
0"
#39
b11 !
b11 %
1"
#40
0"
#41
b100 !
b100 %
1"
#42
0"
#43
b101 !
b101 %
1"
#44
0"
#45
b110 !
b110 %
1"
#46
0"
#47
b111 !
b111 %
1"
#48
0"
#49
b1000 !
b1000 %
1"
#50
0"
#51
b1001 !
b1001 %
1"
#52
0"
#53
b1010 !
b1010 %
1"
#54
0"
#55
b1011 !
b1011 %
1"
#56
0"
#57
b1100 !
b1100 %
1"
#58
0"
#59
b1101 !
b1101 %
1"
#60
0"
#61
b1110 !
b1110 %
1"
#62
0"
#63
b1111 !
b1111 %
1"
#64
0"
#65
b0 !
b0 %
1"
#66
0"
#67
b1 !
b1 %
1"
#68
0"
#69
b10 !
b10 %
1"
#70
0"
#71
b11 !
b11 %
1"
#72
0"
#73
b100 !
b100 %
1"
#74
0"
#75
b101 !
b101 %
1"
#76
0"
#77
b110 !
b110 %
1"
#78
0"
#79
b111 !
b111 %
1"
#80
0"
#81
b1000 !
b1000 %
1"
#82
0"
#83
b1001 !
b1001 %
1"
#84
0"
#85
b1010 !
b1010 %
1"
#86
0"
#87
b1011 !
b1011 %
1"
#88
0"
#89
b1100 !
b1100 %
1"
#90
0"
#91
b1101 !
b1101 %
1"
#92
0"
#93
b1110 !
b1110 %
1"
#94
0"
#95
b1111 !
b1111 %
1"
#96
0"
#97
b0 !
b0 %
1"
#98
0"
#99
b1 !
b1 %
1"
#100
0"
#101
b10 !
b10 %
1"
#102
0"
#103
b11 !
b11 %
1"
#104
0"
#105
b100 !
b100 %
1"
#106
0"
#107
b101 !
b101 %
1"
#108
0"
#109
b110 !
b110 %
1"
#110
0"
#111
b111 !
b111 %
1"
#112
0"
#113
b1000 !
b1000 %
1"
#114
0"
#115
b1001 !
b1001 %
1"
#116
0"
#117
b1010 !
b1010 %
1"
#118
0"
#119
b1011 !
b1011 %
1"
#120
0"
#121
b1100 !
b1100 %
1"
#122
0"
#123
b1101 !
b1101 %
1"
#124
0"
#125
b1110 !
b1110 %
1"
#126
0"
#127
b1111 !
b1111 %
1"
#128
0"
#129
b0 !
b0 %
1"
#130
0"
#131
b1 !
b1 %
1"
#132
0"
#133
b10 !
b10 %
1"
#134
0"
#135
b11 !
b11 %
1"
#136
0"
#137
b100 !
b100 %
1"
#138
0"
#139
b101 !
b101 %
1"
#140
0"
#141
b110 !
b110 %
1"
#142
0"
#143
b111 !
b111 %
1"
#144
0"
#145
b1000 !
b1000 %
1"
#146
0"
#147
b1001 !
b1001 %
1"
#148
0"
#149
b1010 !
b1010 %
1"
#150
0"
#151
b1011 !
b1011 %
1"
#152
0"
#153
b1100 !
b1100 %
1"
#154
0"
#155
b1101 !
b1101 %
1"
#156
0"
#157
b1110 !
b1110 %
1"
#158
0"
#159
b1111 !
b1111 %
1"
#160
0"
#161
b0 !
b0 %
1"
#162
0"
#163
b1 !
b1 %
1"
#164
0"
#165
b10 !
b10 %
1"
#166
0"
#167
b11 !
b11 %
1"
#168
0"
#169
b100 !
b100 %
1"
#170
0"
#171
b101 !
b101 %
1"
#172
0"
#173
b110 !
b110 %
1"
#174
0"
#175
b111 !
b111 %
1"
#176
0"
#177
b1000 !
b1000 %
1"
#178
0"
#179
b1001 !
b1001 %
1"
#180
0"
#181
b1010 !
b1010 %
1"
#182
0"
#183
b1011 !
b1011 %
1"
#184
0"
#185
b1100 !
b1100 %
1"
#186
0"
#187
b1101 !
b1101 %
1"
#188
0"
#189
b1110 !
b1110 %
1"
#190
0"
#191
b1111 !
b1111 %
1"
#192
0"
#193
b0 !
b0 %
1"
#194
0"
#195
b1 !
b1 %
1"
#196
0"
#197
b10 !
b10 %
1"
#198
0"
#199
b11 !
b11 %
1"
#200
0"
#201
b100 !
b100 %
1"
#202
0"
#203
b101 !
b101 %
1"
#204
0"
#205
b110 !
b110 %
1"
#206
0"
#207
b111 !
b111 %
1"
#208
0"
#209
b1000 !
b1000 %
1"
#210
0"
#211
b1001 !
b1001 %
1"
#212
0"
#213
b1010 !
b1010 %
1"
#214
0"
#215
b1011 !
b1011 %
1"
#216
0"
#217
b1100 !
b1100 %
1"
#218
0"
#219
b1101 !
b1101 %
1"
#220
0"
#221
b1110 !
b1110 %
1"
#222
0"
#223
b1111 !
b1111 %
1"
#224
0"
#225
b0 !
b0 %
1"
#226
0"
#227
b1 !
b1 %
1"
#228
0"
#229
b10 !
b10 %
1"
#230
0"
#231
b11 !
b11 %
1"
#232
0"
#233
b100 !
b100 %
1"
#234
0"
#235
b101 !
b101 %
1"
#236
0"
#237
b110 !
b110 %
1"
#238
0"
#239
b111 !
b111 %
1"
#240
0"
#241
b1000 !
b1000 %
1"
#242
0"
#243
b1001 !
b1001 %
1"
#244
0"
#245
b1010 !
b1010 %
1"
#246
0"
#247
b1011 !
b1011 %
1"
#248
0"
#249
b1100 !
b1100 %
1"
#250
0"
#251
b1101 !
b1101 %
1"
#252
0"
#253
b1110 !
b1110 %
1"
#254
0"
#255
b1111 !
b1111 %
1"
#256
0"
#257
b0 !
b0 %
1"
#258
0"
#259
b1 !
b1 %
1"
#260
0"
#261
b10 !
b10 %
1"
#262
0"
#263
b11 !
b11 %
1"
#264
0"
#265
b100 !
b100 %
1"
#266
0"
#267
b101 !
b101 %
1"
#268
0"
#269
b110 !
b110 %
1"
#270
0"
#271
b111 !
b111 %
1"
#272
0"
#273
b1000 !
b1000 %
1"
#274
0"
#275
b1001 !
b1001 %
1"
#276
0"
#277
b1010 !
b1010 %
1"
#278
0"
#279
b1011 !
b1011 %
1"
#280
0"
#281
b1100 !
b1100 %
1"
#282
0"
#283
b1101 !
b1101 %
1"
#284
0"
#285
b1110 !
b1110 %
1"
#286
0"
#287
b1111 !
b1111 %
1"
#288
0"
#289
b0 !
b0 %
1"
#290
0"
#291
b1 !
b1 %
1"
#292
0"
#293
b10 !
b10 %
1"
#294
0"
#295
b11 !
b11 %
1"
#296
0"
#297
b100 !
b100 %
1"
#298
0"
#299
b101 !
b101 %
1"
#300
0"
#301
b110 !
b110 %
1"
#302
0"
#303
b111 !
b111 %
1"
#304
0"
#305
b1000 !
b1000 %
1"
#306
0"
#307
b1001 !
b1001 %
1"
#308
0"
#309
b1010 !
b1010 %
1"
#310
0"
#311
b1011 !
b1011 %
1"
#312
0"
#313
b1100 !
b1100 %
1"
#314
0"
#315
b1101 !
b1101 %
1"
#316
0"
#317
b1110 !
b1110 %
1"
#318
0"
#319
b1111 !
b1111 %
1"
#320
0"
#321
b0 !
b0 %
1"
#322
0"
#323
b1 !
b1 %
1"
#324
0"
#325
b10 !
b10 %
1"
#326
0"
#327
b11 !
b11 %
1"
#328
0"
#329
b100 !
b100 %
1"
#330
0"
#331
b101 !
b101 %
1"
#332
0"
#333
b110 !
b110 %
1"
#334
0"
#335
b111 !
b111 %
1"
#336
0"
#337
b1000 !
b1000 %
1"
#338
0"
#339
b1001 !
b1001 %
1"
#340
0"
#341
b1010 !
b1010 %
1"
#342
0"
#343
b1011 !
b1011 %
1"
#344
0"
#345
b1100 !
b1100 %
1"
#346
0"
#347
b1101 !
b1101 %
1"
#348
0"
#349
b1110 !
b1110 %
1"
#350
0"
#351
b1111 !
b1111 %
1"
#352
0"
#353
b0 !
b0 %
1"
#354
0"
#355
b1 !
b1 %
1"
#356
0"
#357
b10 !
b10 %
1"
#358
0"
#359
b11 !
b11 %
1"
#360
0"
#361
b100 !
b100 %
1"
#362
0"
#363
b101 !
b101 %
1"
#364
0"
#365
b110 !
b110 %
1"
#366
0"
#367
b111 !
b111 %
1"
#368
0"
#369
b1000 !
b1000 %
1"
#370
0"
#371
b1001 !
b1001 %
1"
#372
0"
#373
b1010 !
b1010 %
1"
#374
0"
#375
b1011 !
b1011 %
1"
#376
0"
#377
b1100 !
b1100 %
1"
#378
0"
#379
b1101 !
b1101 %
1"
#380
0"
#381
b1110 !
b1110 %
1"
#382
0"
#383
b1111 !
b1111 %
1"
#384
0"
#385
b0 !
b0 %
1"
#386
0"
#387
b1 !
b1 %
1"
#388
0"
#389
b10 !
b10 %
1"
#390
0"
#391
b11 !
b11 %
1"
#392
0"
#393
b100 !
b100 %
1"
#394
0"
#395
b101 !
b101 %
1"
#396
0"
#397
b110 !
b110 %
1"
#398
0"
#399
b111 !
b111 %
1"
#400
0"
#401
b1000 !
b1000 %
1"
#402
0"
#403
b1001 !
b1001 %
1"
#404
0"
#405
b1010 !
b1010 %
1"
#406
0"
#407
b1011 !
b1011 %
1"
#408
0"
#409
b1100 !
b1100 %
1"
#410
0"
#411
b1101 !
b1101 %
1"
#412
0"
#413
b1110 !
b1110 %
1"
#414
0"
#415
b1111 !
b1111 %
1"
#416
0"
#417
b0 !
b0 %
1"
#418
0"
#419
b1 !
b1 %
1"
#420
0"
#421
b10 !
b10 %
1"
#422
0"
#423
b11 !
b11 %
1"
#424
0"
#425
b100 !
b100 %
1"
#426
0"
#427
b101 !
b101 %
1"
#428
0"
#429
b110 !
b110 %
1"
#430
0"
#431
b111 !
b111 %
1"
#432
0"
#433
b1000 !
b1000 %
1"
#434
0"
#435
b1001 !
b1001 %
1"
#436
0"
#437
b1010 !
b1010 %
1"
#438
0"
#439
b1011 !
b1011 %
1"
#440
0"
#441
b1100 !
b1100 %
1"
#442
0"
#443
b1101 !
b1101 %
1"
#444
0"
#445
b1110 !
b1110 %
1"
#446
0"
#447
b1111 !
b1111 %
1"
#448
0"
#449
b0 !
b0 %
1"
#450
0"
#451
b1 !
b1 %
1"
#452
0"
#453
b10 !
b10 %
1"
#454
0"
#455
b11 !
b11 %
1"
#456
0"
#457
b100 !
b100 %
1"
#458
0"
#459
b101 !
b101 %
1"
#460
0"
#461
b110 !
b110 %
1"
#462
0"
#463
b111 !
b111 %
1"
#464
0"
#465
b1000 !
b1000 %
1"
#466
0"
#467
b1001 !
b1001 %
1"
#468
0"
#469
b1010 !
b1010 %
1"
#470
0"
#471
b1011 !
b1011 %
1"
#472
0"
#473
b1100 !
b1100 %
1"
#474
0"
#475
b1101 !
b1101 %
1"
#476
0"
#477
b1110 !
b1110 %
1"
#478
0"
#479
b1111 !
b1111 %
1"
#480
0"
#481
b0 !
b0 %
1"
#482
0"
#483
b1 !
b1 %
1"
#484
0"
#485
b10 !
b10 %
1"
#486
0"
#487
b11 !
b11 %
1"
#488
0"
#489
b100 !
b100 %
1"
#490
0"
#491
b101 !
b101 %
1"
#492
0"
#493
b110 !
b110 %
1"
#494
0"
#495
b111 !
b111 %
1"
#496
0"
#497
b1000 !
b1000 %
1"
#498
0"
#499
b1001 !
b1001 %
1"
#500
0"
#501
b1010 !
b1010 %
1"
#502
0"
#503
b1011 !
b1011 %
1"
#504
0"
#505
b1100 !
b1100 %
1"
#506
0"
#507
b1101 !
b1101 %
1"
#508
0"
#509
b1110 !
b1110 %
1"
#510
0"
#511
b1111 !
b1111 %
1"
#512
0"
#513
b0 !
b0 %
1"
#514
0"
#515
b1 !
b1 %
1"
#516
0"
#517
b10 !
b10 %
1"
#518
0"
#519
b11 !
b11 %
1"
#520
0"
#521
b100 !
b100 %
1"
#522
0"
#523
b101 !
b101 %
1"
#524
0"
#525
b110 !
b110 %
1"
#526
0"
#527
b111 !
b111 %
1"
#528
0"
#529
b1000 !
b1000 %
1"
#530
0"
#531
b1001 !
b1001 %
1"
#532
0"
#533
b1010 !
b1010 %
1"
#534
0"
#535
b1011 !
b1011 %
1"
#536
0"
#537
b1100 !
b1100 %
1"
#538
0"
#539
b1101 !
b1101 %
1"
#540
0"
#541
b1110 !
b1110 %
1"
#542
0"
#543
b1111 !
b1111 %
1"
#544
0"
#545
b0 !
b0 %
1"
#546
0"
#547
b1 !
b1 %
1"
#548
0"
#549
b10 !
b10 %
1"
