CS207/document.v/lab10/count.v
 module count(Q, clk); 
 output reg  Q; 
 input clk;


always @(posedge clk) 
case(Q)
 0: Q <= Q+1; 
 1: Q <= Q+1; 
 2: Q <= Q+1; 
 3: Q <= Q+1; 
 4: Q <= Q+1; 
 5: Q <= Q+1; 
 6: Q <= Q+1; 
 7: Q <= Q+1; 
 default: Q <= 1; 
 endcase 
 endmodule

  module count_tb; 
  reg CLK; 
  wire Q;

initial begin 
CLK<=1'b1; 
 end
 always @(CLK)
  begin 
  #1 CLK<=!CLK;
   end

 count count_1(Q, CLK);

 initial begin 
 $dumpfile("count.vcd"); 
  $dumpvars(0, count_tb); 
   end

 initial begin 
 #20 $finish; 
  end 
   endmodule

CS207/document.v/lab10/count.vcd
$date
	Wed May 20 09:05:49 2020
$end
$version
	Icarus Verilog
$end
$timescale
	1s
$end
$scope module count_tb $end
$var wire 1 ! Q $end
$var reg 1 " CLK $end
$scope module count_1 $end
$var wire 1 " clk $end
$var reg 1 ! Q $end
$upscope $end
$upscope $end
$enddefinitions $end
#0
$dumpvars
1"
1!
$end
#1
0"
#2
0!
1"
#3
0"
#4
1!
1"
#5
0"
#6
0!
1"
#7
0"
#8
1!
1"
#9
0"
#10
0!
1"
#11
0"
#12
1!
1"
#13
0"
#14
0!
1"
#15
0"
#16
1!
1"
#17
0"
#18
0!
1"
#19
0"
#20
1!
1"
