CS207/lab code/lab9/learn/moore.v
module moore(Y, A, B, X, clk); 
output reg Y; 
output reg A, B; 
input X; 
input clk;

always @(A or B) 
case({A, B}) 
3: Y <= 1'd1;  
default: Y <= 1'd0;
endcase 
always @(posedge clk) 
case({A, B, X}) 
0, 7: {A, B} <= 2'b00; 
1, 2: {A, B} <= 2'b01; 
3, 4: {A, B} <= 2'b10; 
5, 6: {A, B} <= 2'b11; 
default: {A, B} <= 2'b00; 
endcase 
endmodule


 module moore_tb; 
 reg CLK; 
 reg X;
  wire y; 
  wire [1:0] Q;
initial begin 
CLK <= 1'b0; 
X <= 1'b0; 
end
always @(CLK) 
begin 
#1 CLK <= !CLK; 
end
moore moore1(y, Q[1], Q[0], X, CLK);
initial begin 
$dumpfile("moore.vcd"); 
$dumpvars(0, moore_tb); 
end
initial begin 
$monitor("%3t: X = %b, y = %b, Q[1] = %b, Q[0] = %b", $time, X, y, Q[0], Q[1]); 
#2 X <= 1'b0; 
#2 X <= 1'b1; 
#2 X <= 1'b1; 
#2 X <= 1'b1; 
#2 X <= 1'b0; 
#2 X <= 1'b0; 
#2 X <= 1'b1; 
#2 X <= 1'b0; 
#2 X <= 1'b1; 
#2 X <= 1'b1; 
#2 X <= 1'b0; 
#2 $finish; 
end 
endmodule

CS207/document.v/lab9/learn/moore.vcd
$date
	Wed Apr 22 10:48:41 2020
$end
$version
	Icarus Verilog
$end
$timescale
	1s
$end
$scope module moore_tb $end
$var wire 1 ! y $end
$var wire 2 " Q [1:0] $end
$var reg 1 # CLK $end
$var reg 1 $ X $end
$scope module moore1 $end
$var wire 1 $ X $end
$var wire 1 # clk $end
$var reg 1 % A $end
$var reg 1 & B $end
$var reg 1 ! Y $end
$upscope $end
$upscope $end
$enddefinitions $end
#0
$dumpvars
x&
x%
0$
0#
bx "
x!
$end
#1
0!
0%
b0 "
0&
1#
#2
0#
#3
1#
#4
0#
1$
#5
b1 "
1&
1#
#6
0#
#7
1%
b10 "
0&
1#
#8
0#
#9
1!
b11 "
1&
1#
#10
0#
0$
#11
1#
#12
0#
#13
1#
#14
0#
1$
#15
0!
0%
b0 "
0&
1#
#16
0#
0$
#17
1#
#18
0#
1$
#19
b1 "
1&
1#
#20
0#
#21
1%
b10 "
0&
1#
#22
0#
0$
