CS207/lab code/lab7/dff.v
module dff(Q, D, CLK);
input CLK;
input D;
output Q;
reg Q;
always@(posedge CLK) begin
case(D)
0 : Q<=0;
1 : Q<=1;
endcase
    end


endmodule

CS207/document.v/lab7/dff_tb.v
module dff_tb;
reg CLK; 
reg D; 
wire Q, nQ; 
initial CLK <= 1'b1;

always @(CLK) 
begin 
#1 CLK<=!CLK; 
end

dff mysr(Q, D, CLK);
initial begin 
$dumpfile("dff.vcd"); 
$dumpvars(0,dff_tb); 
end

initial begin 
$monitor("%3t: D=%b, Q = %b", $time, D,Q); 
#5 D <= 1'b0; //R <= 1'b0; 
//#5 S <= 1'b1; R <= 1'b1;
#4 D <= 1'b1; //R <= 1'b0; 
#6 D <= 1'b0; //R <= 1'b0; 
#5 D <= 1'b0; //R <= 1'b1; 
#5 D <= 1'b0; //R <= 1'b0; 
#5 D <= 1'b1; //R <= 1'b0; 
#5 D <= 1'b0; //R <= 1'b0; 
#5 $finish; 
end 
 endmodule

CS207/lab code/lab7/dff.vcd
$date
	Wed Apr 08 00:58:49 2020
$end
$version
	Icarus Verilog
$end
$timescale
	1s
$end
$scope module dff_tb $end
$var wire 1 ! Q $end
$var reg 1 " CLK $end
$var reg 1 # D $end
$scope module mysr $end
$var wire 1 " CLK $end
$var wire 1 # D $end
$var reg 1 ! Q $end
$upscope $end
$upscope $end
$enddefinitions $end
#0
$dumpvars
x#
1"
x!
$end
#1
0"
#2
1"
#3
0"
#4
1"
#5
0"
0#
#6
0!
1"
#7
0"
#8
1"
#9
0"
1#
#10
1!
1"
#11
0"
#12
1"
#13
0"
#14
1"
#15
0"
0#
#16
0!
1"
#17
0"
#18
1"
#19
0"
#20
1"
#21
0"
#22
1"
#23
0"
#24
1"
#25
0"
#26
1"
#27
0"
#28
1"
#29
0"
#30
1!
1"
1#
#31
0"
#32
1"
#33
0"
#34
1"
#35
0"
0#
#36
0!
1"
