CS207/lab code/lab7/dlatch.v
module dlatch(Q, nQ, D, G);
input G;
input D;
output Q, nQ;
reg Q;
reg nQ;
always @(G) begin
    if(G) begin
    case(D) 
    0 : {Q,nQ}<=2'b01;
    1 : {Q,nQ}<=2'b10;
    endcase
    end
    
end
endmodule

CS207/lab code/lab7/dlatch_tb.v
module dlatch_tb;
reg CLK; 
reg D; 
wire Q, nQ; 
initial CLK <= 1'b1;

always @(CLK) 
begin 
#1 CLK<=!CLK; 
end

dlatch mysr(Q, nQ, D, CLK);
initial begin 
$dumpfile("dl.vcd"); 
$dumpvars(0,dlatch_tb); 
end

initial begin 
$monitor("%3t: Q = %b, nQ = %b", $time, Q, nQ); 
#5 D <= 1'b0; //R <= 1'b0; 
//#5 S <= 1'b1; R <= 1'b1;
#5 D <= 1'b1; //R <= 1'b0; 
#5 D <= 1'b0; //R <= 1'b0; 
#5 D <= 1'b0; //R <= 1'b1; 
#5 D <= 1'b0; //R <= 1'b0; 
#5 D <= 1'b1; //R <= 1'b0; 
#5 D <= 1'b0; //R <= 1'b0; 
#5 $finish; 
end 
 endmodule

CS207/lab code/lab7/dl.vcd
$date
	Wed Apr 08 10:46:39 2020
$end
$version
	Icarus Verilog
$end
$timescale
	1s
$end
$scope module dlatch_tb $end
$var wire 1 ! nQ $end
$var wire 1 " Q $end
$var reg 1 # CLK $end
$var reg 1 $ D $end
$scope module mysr $end
$var wire 1 $ D $end
$var wire 1 # G $end
$var reg 1 " Q $end
$var reg 1 ! nQ $end
$upscope $end
$upscope $end
$enddefinitions $end
#0
$dumpvars
x$
1#
x"
x!
$end
#1
0#
#2
1#
#3
0#
#4
1#
#5
0#
0$
#6
0"
1!
1#
#7
0#
#8
1#
#9
0#
#10
1"
0!
1#
1$
#11
0#
#12
1#
#13
0#
#14
1#
#15
0#
0$
#16
0"
1!
1#
#17
0#
#18
1#
#19
0#
#20
1#
#21
0#
#22
1#
#23
0#
#24
1#
#25
0#
#26
1#
#27
0#
#28
1#
#29
0#
#30
1"
0!
1#
1$
#31
0#
#32
1#
#33
0#
#34
1#
#35
0#
0$
#36
0"
1!
1#
