CS207/document.v/lab9/test.v
module moore(Z, Q, X, clk);
output reg Z; 
output reg [1:0]Q;
input [1:0]X;
input clk;

always @(Q[0] or Q[1])
case({Q[1], Q[0]})
1, 2: Z <= 1'd1;  
default: Z <= 1'd0;
endcase   

always @(posedge clk) 
case({Q[1], Q[0], X[1], X[0]}) 
0, 3, 7, 11, 12, 15: {Q[1], Q[0]} <= 2'b00; 
1, 4, 5: {Q[1], Q[0]} <= 2'b01; 
2, 8, 10: {Q[1], Q[0]} <= 2'b10; 
6, 9, 13, 14: {Q[1], Q[0]} <= 2'b11; 
default: {Q[1], Q[0]} <= 2'b00; 
endcase 
endmodule

CS207/document.v/lab9/moore_tb_2.v
module moore_tb; 
  reg CLK; 
  reg [1:0]X;
  wire Z;
  wire [1:0] Q;
  initial begin 
  CLK <= 1'b0; 
  X[1] <= 1'b0; 
  X[0] <=1'b0;
  end
  always @(CLK) 
  begin 
  #1 CLK<=!CLK;
   end

 always@(X[1])
 begin
 #2 X[1]<=!X[1];
  end
always@(X[0])
begin
  #5 X[0]<=!X[0];
  end

 moore moore1(Z, Q, X, CLK);
initial begin 
$dumpfile("moore.vcd"); 
$dumpvars(0, moore_tb);
 end
initial begin
$monitor("%3t: %b%b %b%b %b", $time,  Q[1], Q[0],X[1],X[0],Z);
//#2 X <= 2'b00; 
//#2 X <= 2'b00; 
//#2 X <= 2'b01; 
//#2 X <= 2'b01; 
//#2 X <= 2'b10; 
//#2 X <= 2'b10; 
//#2 X <= 2'b11; 
//#2 X <= 2'b11; 
//#2 X <= 2'b00; 
//#2 X <= 2'b00; 

#30 $finish;
 end
  endmodule

CS207/document.v/lab9/moore.vcd
$date
	Wed Apr 22 10:46:39 2020
$end
$version
	Icarus Verilog
$end
$timescale
	1s
$end
$scope module moore_tb $end
$var wire 1 ! Z $end
$var wire 2 " Q [1:0] $end
$var reg 1 # CLK $end
$var reg 2 $ X [1:0] $end
$scope module moore1 $end
$var wire 2 % X [1:0] $end
$var wire 1 # clk $end
$var reg 2 & Q [1:0] $end
$var reg 1 ! Z $end
$upscope $end
$upscope $end
$enddefinitions $end
#0
$dumpvars
bx &
b0 %
b0 $
0#
bx "
x!
$end
#1
0!
b0 "
b0 &
1#
#2
0#
b10 $
b10 %
#3
1#
b11 $
b11 %
#4
0#
b1 $
b1 %
#5
1!
b1 "
b1 &
1#
#6
0#
b10 $
b10 %
#7
0!
b11 "
b11 &
1#
#8
0#
b0 $
b0 %
#9
1#
b1 $
b1 %
#10
0#
b11 $
b11 %
#11
b0 "
b0 &
1#
#12
0#
b0 $
b0 %
#13
1#
#14
0#
b10 $
b10 %
#15
1#
b11 $
b11 %
#16
0#
b1 $
b1 %
#17
1!
b1 "
b1 &
1#
